<?xml version = '1.0' encoding = 'UTF-8'?>
<Relation class="oracle.dbtools.crest.model.design.logical.Relation" name="Event_Fire_LGA_FK" directorySegmentName="seg_0" id="3667765D-BD0A-6058-F955-3285A96EE5A9">
<createdBy>shene</createdBy>
<createdTime>2021-09-14 09:41:25 UTC</createdTime>
<ownerDesignName>FDAS_Modeller</ownerDesignName>
<sourcePk>AB64FE70-9729-AA33-E207-A7623C563AA8</sourcePk>
<identifying>false</identifying>
<optionalSource>true</optionalSource>
<optionalTarget>false</optionalTarget>
<sourceCardinality>1</sourceCardinality>
<sourceEntity>2B18CE1C-900F-FA2C-569B-AF6A2ECD83BE</sourceEntity>
<targetCardinalityString>*</targetCardinalityString>
<targetEntity>C0C411C2-AE89-D280-2AB0-EB6C59F2B86F</targetEntity>
<transferable>true</transferable>
<deleteRule>NO ACTION</deleteRule>
</Relation>
